estd/__init__.py
estd/mail.py
estd/utils.py
estd-0.0.4.dist-info/METADATA
estd-0.0.4.dist-info/WHEEL
estd-0.0.4.dist-info/top_level.txt
estd-0.0.4.dist-info/RECORD
