Metadata-Version: 2.1
Name: estd
Version: 0.0.4
Summary: Extended standard library
Home-page: https://gitee.com/xhqsm/estd/
Author: singchen
Author-email: xhqsm@qq.com
License: MIT
Platform: UNKNOWN
